{
  "asOf": "2025-10-06",
  "metrics": {
    "vix": 16.649999618530273,
    "currentSP": 6715.7900390625,
    "ma125": 6121.045828125,
    "bond10Y": 4,
    "putCall": 0.95,
    "junkSpread": 2.81,
    "spHigh": 6715.7900390625,
    "spLow": 4982.77001953125,
    "usdDxy": 103,
    "volatility": 0.12,
    "correlation": 0.65,
    "sentiment": 66,
    "technical": 71,
    "economic": 75,
    "global": 82,
    "dollarStrength": 50
  },
  "scores": {
    "vixScore": 81,
    "momentumScore": 99,
    "safeHavenScore": 60,
    "putCallScore": 50,
    "junkScore": 86,
    "breadthScore": 100,
    "volumeScore": 65,
    "volatilityScore": 100,
    "correlationScore": 92,
    "sentimentScore": 66,
    "technicalScore": 71,
    "economicScore": 75,
    "globalScore": 82,
    "dollarStrength": 50,
    "finalScore": 81
  }
}